toolbox/__init__.py
toolbox/bigquery_sink/__init__.py
toolbox/bigquery_sink/bulk_sink.py
toolbox/bigquery_sink/sheet_sink.py
toolbox/bigquery_sink/utils/__init__.py
toolbox/bigquery_sink/utils/generate_id.py
toolbox/bigquery_sink/utils/nest.py
toolbox_bigquery_sink-0.0.33.dist-info/licenses/LICENSE
toolbox_bigquery_sink-0.0.33.dist-info/METADATA
toolbox_bigquery_sink-0.0.33.dist-info/WHEEL
toolbox_bigquery_sink-0.0.33.dist-info/top_level.txt
toolbox_bigquery_sink-0.0.33.dist-info/RECORD
