Metadata-Version: 2.4
Name: toolbox-bigquery-sink
Version: 0.0.33
Summary: Tooling to write data to google bigquery
Home-page: http://github.com/nziehn/toolbox-bigquery-sink
Author: Nils Ziehn
Author-email: nziehn@gmail.com
License: MIT
License-File: LICENSE
Requires-Dist: google-cloud-storage>=1.26.0
Requires-Dist: google-cloud-bigquery>=1.24.0
Dynamic: author
Dynamic: author-email
Dynamic: home-page
Dynamic: license
Dynamic: license-file
Dynamic: requires-dist
Dynamic: summary
